test/__init__.py
rwalang-0.0.3.dist-info/LICENSE
rwalang-0.0.3.dist-info/METADATA
rwalang-0.0.3.dist-info/WHEEL
rwalang-0.0.3.dist-info/top_level.txt
rwalang-0.0.3.dist-info/RECORD
