Metadata-Version: 2.1
Name: rwalang
Version: 0.0.3
Summary: A fast language detection package for Ikinyarwanda(Native language of Rwandans)
Home-page: UNKNOWN
Author: Igwaneza Bruce
Author-email: knowbeeinc@gmail.com
License: MIT
Keywords: detect language,rwanda,ikinyarwanda,u rwanda
Platform: UNKNOWN
Classifier: Programming Language :: Python
Classifier: Programming Language :: Python :: 3.8
Classifier: Programming Language :: Python :: 3.7
Classifier: Programming Language :: Python :: 3.6
Classifier: Programming Language :: Python :: 3.5
Classifier: Natural Language :: Afrikaans
Classifier: Intended Audience :: Developers
Classifier: Intended Audience :: Education
Classifier: Operating System :: OS Independent
Requires-Python: >=3.6
